mapio/__init__.py
mapio/basemapcity.py
mapio/dataset.py
mapio/gdal.py
mapio/geodict.py
mapio/gmt.py
mapio/grid2d.py
mapio/gridbase.py
mapio/gridcontainer.py
mapio/multihaz.py
mapio/multiple.py
mapio/reader.py
mapio/shake.py
mapio/writer.py
mapio-0.8.11.dist-info/LICENSE.md
mapio-0.8.11.dist-info/METADATA
mapio-0.8.11.dist-info/WHEEL
mapio-0.8.11.dist-info/top_level.txt
mapio-0.8.11.dist-info/RECORD
