Metadata-Version: 2.1
Name: mapio
Version: 0.8.11
Summary: Reading/resampling of raster files (esp. across 180 meridian)
Author-email: Mike Hearne <mhearne@usgs.gov>
License: License
Keywords: comcat,earthquake
Requires-Python: >=3.9
License-File: LICENSE.md
Requires-Dist: esi-utils-io
Requires-Dist: geopy
Requires-Dist: h5py
Requires-Dist: matplotlib
Requires-Dist: netcdf4==1.7.1.post1
Requires-Dist: pyproj
Requires-Dist: rasterio
Requires-Dist: scipy
Requires-Dist: shapely
Provides-Extra: build
Requires-Dist: build; extra == "build"
Requires-Dist: twine; extra == "build"
Requires-Dist: check-wheel-contents; extra == "build"
Provides-Extra: dev
Requires-Dist: build>=0.7.0; extra == "dev"
Requires-Dist: black>=21; extra == "dev"
Requires-Dist: flake8>=3.9; extra == "dev"
Requires-Dist: ipython>=7.26; extra == "dev"
Requires-Dist: notebook>=6.4.1; extra == "dev"
Provides-Extra: test
Requires-Dist: pytest>=6.2; extra == "test"
Requires-Dist: pytest-cov>=2.12.0; extra == "test"
